mriqc_comparison-1.1-py3.8-nspkg.pth
mriqc_comparison/bids.py
mriqc_comparison/info.py
mriqc_comparison/local_mriqc_stats.py
mriqc_comparison/plots.py
mriqc_comparison/utils.py
mriqc_comparison-1.1.dist-info/LICENSE
mriqc_comparison-1.1.dist-info/METADATA
mriqc_comparison-1.1.dist-info/WHEEL
mriqc_comparison-1.1.dist-info/namespace_packages.txt
mriqc_comparison-1.1.dist-info/top_level.txt
mriqc_comparison-1.1.dist-info/RECORD
