Metadata-Version: 2.1
Name: mriqc-comparison
Version: 1.1
Summary: Compares MRIQC IQMs
Home-page: https://github.com/cbinyu/mriqc_comparison
Author: Pablo Velasco
Author-email: pablo.velasco@nyu.edu
License: MIT
Platform: UNKNOWN
Classifier: Environment :: Console
Classifier: Intended Audience :: Science/Research
Classifier: License :: OSI Approved :: BSD License
Classifier: Programming Language :: Python :: 3.6
Classifier: Programming Language :: Python :: 3.7
Classifier: Programming Language :: Python :: 3.8
Classifier: Topic :: Scientific/Engineering
Requires-Python: >=3.6
Requires-Dist: pandas (>=0.25.0)
Requires-Dist: numpy (>=1.17.1)
Requires-Dist: mriqc (>=0.13.0)
Provides-Extra: all
Requires-Dist: pytest ; extra == 'all'
Provides-Extra: tests
Requires-Dist: pytest ; extra == 'tests'
